lupapy-2.2.dist-info/RECORD
lupapy-2.2.dist-info/WHEEL
lupapy-2.2.dist-info/top_level.txt
lupapy-2.2.dist-info/LICENSE.txt
lupapy-2.2.dist-info/METADATA
lupa/version.py
lupa/__init__.py
lupa/lua52.pypy310-pp73-darwin.so
lupa/lua51.pypy310-pp73-darwin.so
lupa/lua53.pypy310-pp73-darwin.so
lupa/lua54.pypy310-pp73-darwin.so
