Metadata-Version: 2.1
Name: lupapy
Version: 2.2
Summary: Python wrapper around Lua and LuaJIT
Home-page: https://github.com/scoder/lupa
Author: Stefan Behnel
Author-email: stefan_ml@behnel.de
Maintainer: Michal Plichta
Maintainer-email: mplichta@gmail.com
License: MIT style
Project-URL: Documentation, https://github.com/scoder/lupa/blob/master/README.rst
Project-URL: Changelog, https://github.com/scoder/lupa/blob/master/CHANGES.rst
Project-URL: Source, https://github.com/scoder/lupa.git
Classifier: Development Status :: 5 - Production/Stable
Classifier: Intended Audience :: Developers
Classifier: Intended Audience :: Information Technology
Classifier: License :: OSI Approved :: MIT License
Classifier: Programming Language :: Cython
Classifier: Programming Language :: Python :: 3
Classifier: Programming Language :: Python :: 3.6
Classifier: Programming Language :: Python :: 3.7
Classifier: Programming Language :: Python :: 3.8
Classifier: Programming Language :: Python :: 3.9
Classifier: Programming Language :: Python :: 3.10
Classifier: Programming Language :: Python :: 3.11
Classifier: Programming Language :: Python :: 3.12
Classifier: Programming Language :: Python :: 3.13
Classifier: Programming Language :: Lua
Classifier: Programming Language :: Other Scripting Engines
Classifier: Operating System :: OS Independent
Classifier: Topic :: Software Development
License-File: LICENSE.txt
